{
    "port": "4455",
    "password": "yZvliMIbtVz7qyE3",
    "aePath": "C:\\Program Files\\Adobe\\Adobe After Effects 2024\\Support Files\\AfterFX.exe",
    "aepPath": "C:\\Users\\marks\\OneDrive\\Documents\\SNU\\\ub3d9\uc544\ub9ac\\SUB\\SUB Sports\\SUB SPORTS TEMPLATE\\SUBsports (converted) - \ubcf5\uc0ac\ubcf8.aep",
    "compName": "start_screen\ntest",
    "outputPath": "C:\\Users\\marks\\OneDrive\\Desktop\\start_screen.mov\nC:\\Users\\marks\\OneDrive\\Desktop\\test.mov",
    "csvPath": "C:\\Users\\marks\\OneDrive\\Documents\\SNU\\\ub3d9\uc544\ub9ac\\SUB\\SUB Sports\\SUB SPORTS TEMPLATE\\team_info_converted.csv"
}